README.md
setup.py
shapley/__init__.py
shapley/solution_concept.py
shapley/version.py
shapley.egg-info/PKG-INFO
shapley.egg-info/SOURCES.txt
shapley.egg-info/dependency_links.txt
shapley.egg-info/requires.txt
shapley.egg-info/top_level.txt
shapley/solvers/__init__.py
shapley/solvers/exact_enumeration.py
shapley/solvers/expected_marginal_contributions.py
shapley/solvers/multilinear_extension.py
shapley/solvers/permutation_sampler.py