Metadata-Version: 1.1
Name: shapley
Version: 1.0.3
Summary: A general purpose library to quantify the value of classifiers in an ensemble.
Home-page: https://github.com/benedekrozemberczki/shapley
Author: Benedek Rozemberczki
Author-email: benedek.rozemberczki@gmail.com
License: MIT
Download-URL: https://github.com/benedekrozemberczki/shapley/archive/v_10003.tar.gz
Keywords: shapley,random-forest,data-science,shap,fairness,ensemble,expert-system,explanability,voting-classifier,classifier,machine-learning,deep-learning,deeplearning,game-theory,cooperative-game
Platform: UNKNOWN
Classifier: Development Status :: 3 - Alpha
Classifier: Intended Audience :: Developers
Classifier: Topic :: Software Development :: Build Tools
Classifier: License :: OSI Approved :: MIT License
Classifier: Programming Language :: Python :: 3.7
